[
  {
    "input": [],
    "output": "code",
    "rarity": "common"
  },
  {
    "input": [],
    "output": "network",
    "rarity": "common"
  },
  {
    "input": [],
    "output": "cryptography",
    "rarity": "common"
  },
  {
    "input": [],
    "output": "consensus",
    "rarity": "common"
  },
  {
    "input": [
      "code",
      "network"
    ],
    "output": "internet",
    "rarity": "common"
  },
  {
    "input": [
      "code",
      "cryptography"
    ],
    "output": "hash",
    "rarity": "common"
  },
  {
    "input": [
      "code",
      "consensus"
    ],
    "output": "smart_contract",
    "rarity": "uncommon"
  },
  {
    "input": [
      "cryptography",
      "consensus"
    ],
    "output": "blockchain",
    "rarity": "uncommon"
  },
  {
    "input": [
      "blockchain",
      "code"
    ],
    "output": "cryptocurrency",
    "rarity": "uncommon"
  },
  {
    "input": [
      "network",
      "consensus"
    ],
    "output": "peer-to-peer",
    "rarity": "common"
  },
  {
    "input": [
      "network",
      "interoperability"
    ],
    "output": "bridge",
    "rarity": "uncommon"
  },
  {
    "input": [
      "blockchain",
      "network"
    ],
    "output": "node",
    "rarity": "common"
  },
  {
    "input": [
      "cryptocurrency",
      "consensus"
    ],
    "output": "mining",
    "rarity": "uncommon"
  },
  {
    "input": [
      "mining",
      "hash"
    ],
    "output": "proof_of_work",
    "rarity": "rare"
  },
  {
    "input": [
      "cryptocurrency",
      "cryptography"
    ],
    "output": "wallet",
    "rarity": "common"
  },
  {
    "input": [
      "wallet",
      "cryptography"
    ],
    "output": "private_key",
    "rarity": "uncommon"
  },
  {
    "input": [
      "private_key",
      "cryptography"
    ],
    "output": "public_key",
    "rarity": "uncommon"
  },
  {
    "input": [
      "blockchain",
      "consensus"
    ],
    "output": "block",
    "rarity": "common"
  },
  {
    "input": [
      "blockchain",
      "hash"
    ],
    "output": "merkle_tree",
    "rarity": "rare"
  },
  {
    "input": [
      "blockchain",
      "smart_contract"
    ],
    "output": "dapp",
    "rarity": "rare"
  },
  {
    "input": [
      "dapp",
      "consensus"
    ],
    "output": "dao",
    "rarity": "epic"
  },
  {
    "input": [
      "smart_contract",
      "consensus"
    ],
    "output": "staking",
    "rarity": "uncommon"
  },
  {
    "input": [
      "staking",
      "consensus"
    ],
    "output": "proof_of_stake",
    "rarity": "rare"
  },
  {
    "input": [
      "blockchain",
      "peer-to-peer"
    ],
    "output": "mainnet",
    "rarity": "uncommon"
  },
  {
    "input": [
      "mainnet",
      "code"
    ],
    "output": "testnet",
    "rarity": "uncommon"
  },
  {
    "input": [
      "cryptography",
      "proof_of_work"
    ],
    "output": "zero-knowledge_proof",
    "rarity": "epic"
  },
  {
    "input": [
      "cryptocurrency",
      "smart_contract"
    ],
    "output": "token",
    "rarity": "common"
  },
  {
    "input": [
      "token",
      "dao"
    ],
    "output": "governance_token",
    "rarity": "rare"
  },
  {
    "input": [
      "blockchain",
      "internet"
    ],
    "output": "web3",
    "rarity": "rare"
  },
  {
    "input": [
      "web3",
      "smart_contract"
    ],
    "output": "smart_contract_platform",
    "rarity": "rare"
  },
  {
    "input": [
      "blockchain",
      "disagreement"
    ],
    "output": "fork",
    "rarity": "uncommon"
  },
  {
    "input": [
      "fork",
      "consensus"
    ],
    "output": "hard_fork",
    "rarity": "rare"
  },
  {
    "input": [
      "fork",
      "code"
    ],
    "output": "soft_fork",
    "rarity": "rare"
  },
  {
    "input": [
      "blockchain",
      "bridge"
    ],
    "output": "sidechain",
    "rarity": "rare"
  },
  {
    "input": [
      "sidechain",
      "proof_of_stake"
    ],
    "output": "layer_2",
    "rarity": "epic"
  },
  {
    "input": [
      "layer 2",
      "smart_contract"
    ],
    "output": "rollup",
    "rarity": "epic"
  },
  {
    "input": [
      "rollup",
      "zero-knowledge_proof"
    ],
    "output": "zk-rollup",
    "rarity": "legendary"
  },
  {
    "input": [
      "block",
      "consensus"
    ],
    "output": "finality",
    "rarity": "uncommon"
  },
  {
    "input": [
      "cryptocurrency",
      "peer-to-peer"
    ],
    "output": "exchange",
    "rarity": "uncommon"
  },
  {
    "input": [
      "exchange",
      "smart_contract"
    ],
    "output": "dex",
    "rarity": "rare"
  },
  {
    "input": [
      "dex",
      "token"
    ],
    "output": "liquidity_pool",
    "rarity": "rare"
  },
  {
    "input": [
      "liquidity_pool",
      "staking"
    ],
    "output": "yield_farming",
    "rarity": "epic"
  },
  {
    "input": [
      "blockchain",
      "blockchain"
    ],
    "output": "interoperability",
    "rarity": "rare"
  },
  {
    "input": [
      "interoperability",
      "smart_contract"
    ],
    "output": "cross-chain_bridge",
    "rarity": "epic"
  },
  {
    "input": [
      "smart_contract",
      "network"
    ],
    "output": "oracle",
    "rarity": "rare"
  },
  {
    "input": [
      "oracle",
      "consensus"
    ],
    "output": "decentralized_oracle_network",
    "rarity": "epic"
  },
  {
    "input": [
      "private_key",
      "hash"
    ],
    "output": "digital_signature",
    "rarity": "uncommon"
  },
  {
    "input": [
      "digital_signature",
      "wallet"
    ],
    "output": "multi-sig_wallet",
    "rarity": "rare"
  },
  {
    "input": [
      "node",
      "proof_of_stake"
    ],
    "output": "validator",
    "rarity": "rare"
  },
  {
    "input": [
      "smart_contract",
      "block"
    ],
    "output": "gas",
    "rarity": "common"
  },
  {
    "input": [
      "gas",
      "consensus"
    ],
    "output": "gas_limit",
    "rarity": "uncommon"
  },
  {
    "input": [
      "gas",
      "network"
    ],
    "output": "gas_price",
    "rarity": "uncommon"
  },
  {
    "input": [
      "hash",
      "block"
    ],
    "output": "blockchain_explorer",
    "rarity": "rare"
  },
  {
    "input": [
      "smart_contract",
      "code"
    ],
    "output": "solidity",
    "rarity": "uncommon"
  },
  {
    "input": [
      "solidity",
      "code"
    ],
    "output": "evm",
    "rarity": "rare"
  },
  {
    "input": [
      "evm",
      "smart_contract_platform"
    ],
    "output": "ethereum",
    "rarity": "epic"
  },
  {
    "input": [
      "ethereum",
      "layer_2"
    ],
    "output": "optimism",
    "rarity": "epic"
  },
  {
    "input": [
      "optimism",
      "rollup"
    ],
    "output": "ovm",
    "rarity": "legendary"
  },
  {
    "input": [
      "smart_contract",
      "solidity"
    ],
    "output": "abi",
    "rarity": "uncommon"
  },
  {
    "input": [
      "abi",
      "code"
    ],
    "output": "web3.js",
    "rarity": "rare"
  },
  {
    "input": [
      "web3.js",
      "dapp"
    ],
    "output": "metamask",
    "rarity": "rare"
  },
  {
    "input": [
      "blockchain",
      "governance_token"
    ],
    "output": "quadratic_voting",
    "rarity": "epic"
  },
  {
    "input": [
      "quadratic_voting",
      "dao"
    ],
    "output": "gitcoin",
    "rarity": "legendary"
  },
  {
    "input": [
      "ethereum",
      "gas"
    ],
    "output": "eip-1559",
    "rarity": "rare"
  },
  {
    "input": [
      "eip-1559",
      "consensus"
    ],
    "output": "fee_market",
    "rarity": "epic"
  },
  {
    "input": [
      "ethereum",
      "proof_of_stake"
    ],
    "output": "beacon_chain",
    "rarity": "epic"
  },
  {
    "input": [
      "beacon_chain",
      "ethereum"
    ],
    "output": "the_merge",
    "rarity": "legendary"
  },
  {
    "input": [
      "smart_contract",
      "zero-knowledge_proof"
    ],
    "output": "zk-snark",
    "rarity": "epic"
  },
  {
    "input": [
      "blockchain",
      "privacy"
    ],
    "output": "monero",
    "rarity": "epic"
  },
  {
    "input": [
      "monero",
      "cryptography"
    ],
    "output": "ring_signature",
    "rarity": "legendary"
  },
  {
    "input": [
      "smart_contract",
      "ethereum"
    ],
    "output": "erc-20",
    "rarity": "rare"
  },
  {
    "input": [
      "erc-20",
      "token"
    ],
    "output": "fungible_token",
    "rarity": "uncommon"
  },
  {
    "input": [
      "smart_contract",
      "digital_signature"
    ],
    "output": "erc-721",
    "rarity": "rare"
  },
  {
    "input": [
      "erc-721",
      "token"
    ],
    "output": "nft",
    "rarity": "epic"
  },
  {
    "input": [
      "blockchain",
      "solidity"
    ],
    "output": "bytecode",
    "rarity": "uncommon"
  },
  {
    "input": [
      "Bytecode",
      "evm"
    ],
    "output": "opcodes",
    "rarity": "rare"
  },
  {
    "input": [
      "opcodes",
      "gas"
    ],
    "output": "gas_optimization",
    "rarity": "epic"
  },
  {
    "input": [
      "smart_contract",
      "privacy"
    ],
    "output": "tornado_cash",
    "rarity": "epic"
  },
  {
    "input": [
      "tornado_cash",
      "zk-snark"
    ],
    "output": "mixer",
    "rarity": "legendary"
  },
  {
    "input": [
      "node",
      "consensus"
    ],
    "output": "bft",
    "rarity": "rare"
  },
  {
    "input": [
      "bft",
      "proof_of_stake"
    ],
    "output": "tendermint",
    "rarity": "epic"
  },
  {
    "input": [
      "tendermint",
      "blockchain"
    ],
    "output": "cosmos",
    "rarity": "legendary"
  },
  {
    "input": [
      "blockchain",
      "scalability"
    ],
    "output": "state_channels",
    "rarity": "rare"
  },
  {
    "input": [
      "state_channels",
      "cryptocurrency"
    ],
    "output": "lightning_network",
    "rarity": "epic"
  },
  {
    "input": [
      "block",
      "block"
    ],
    "output": "timestamp",
    "rarity": "common"
  },
  {
    "input": [
      "timestamp",
      "block"
    ],
    "output": "time",
    "rarity": "uncommon"
  },
  {
    "input": [
      "network",
      "time"
    ],
    "output": "latency",
    "rarity": "common"
  },
  {
    "input": [
      "blockchain",
      "latency"
    ],
    "output": "scalability",
    "rarity": "uncommon"
  },
  {
    "input": [
      "consensus",
      "community"
    ],
    "output": "disagreement",
    "rarity": "common"
  },
  {
    "input": [
      "internet",
      "human"
    ],
    "output": "community",
    "rarity": "common"
  },
  {
    "input": [
      "internet",
      "community"
    ],
    "output": "privacy",
    "rarity": "common"
  },
  {
    "input": [
      "internet",
      "internet"
    ],
    "output": "human",
    "rarity": "common"
  },
  {
    "input": [
      "unicorn",
      "dex"
    ],
    "output": "uniswap",
    "rarity": "hidden"
  }
]